shellphish_afl/__init__.py
shellphish_afl-1.2.2.data/data/bin/afl-cgc/afl-as
shellphish_afl-1.2.2.data/data/bin/afl-cgc/afl-clang
shellphish_afl-1.2.2.data/data/bin/afl-cgc/afl-clang++
shellphish_afl-1.2.2.data/data/bin/afl-cgc/afl-fuzz
shellphish_afl-1.2.2.data/data/bin/afl-cgc/afl-g++
shellphish_afl-1.2.2.data/data/bin/afl-cgc/afl-gcc
shellphish_afl-1.2.2.data/data/bin/afl-cgc/afl-gotcpu
shellphish_afl-1.2.2.data/data/bin/afl-cgc/afl-showmap
shellphish_afl-1.2.2.data/data/bin/afl-cgc/afl-tmin
shellphish_afl-1.2.2.data/data/bin/afl-cgc/afl-whatsup
shellphish_afl-1.2.2.data/data/bin/afl-cgc/as
shellphish_afl-1.2.2.data/data/bin/afl-cgc/.git/hooks/applypatch-msg.sample
shellphish_afl-1.2.2.data/data/bin/afl-cgc/.git/hooks/commit-msg.sample
shellphish_afl-1.2.2.data/data/bin/afl-cgc/.git/hooks/fsmonitor-watchman.sample
shellphish_afl-1.2.2.data/data/bin/afl-cgc/.git/hooks/post-update.sample
shellphish_afl-1.2.2.data/data/bin/afl-cgc/.git/hooks/pre-applypatch.sample
shellphish_afl-1.2.2.data/data/bin/afl-cgc/.git/hooks/pre-commit.sample
shellphish_afl-1.2.2.data/data/bin/afl-cgc/.git/hooks/pre-merge-commit.sample
shellphish_afl-1.2.2.data/data/bin/afl-cgc/.git/hooks/pre-push.sample
shellphish_afl-1.2.2.data/data/bin/afl-cgc/.git/hooks/pre-rebase.sample
shellphish_afl-1.2.2.data/data/bin/afl-cgc/.git/hooks/pre-receive.sample
shellphish_afl-1.2.2.data/data/bin/afl-cgc/.git/hooks/prepare-commit-msg.sample
shellphish_afl-1.2.2.data/data/bin/afl-cgc/.git/hooks/push-to-checkout.sample
shellphish_afl-1.2.2.data/data/bin/afl-cgc/.git/hooks/update.sample
shellphish_afl-1.2.2.data/data/bin/afl-cgc/experimental/asan_cgroups/limit_memory.sh
shellphish_afl-1.2.2.data/data/bin/afl-cgc/experimental/clang_asm_normalize/as
shellphish_afl-1.2.2.data/data/bin/afl-cgc/experimental/crash_triage/triage_crashes.sh
shellphish_afl-1.2.2.data/data/bin/afl-cgc/experimental/distributed_fuzzing/sync_script.sh
shellphish_afl-1.2.2.data/data/bin/afl-cgc/qemu_mode/build_qemu_support.sh
shellphish_afl-1.2.2.dist-info/METADATA
shellphish_afl-1.2.2.dist-info/WHEEL
shellphish_afl-1.2.2.dist-info/top_level.txt
shellphish_afl-1.2.2.dist-info/RECORD
