Metadata-Version: 2.1
Name: shellphish-afl
Version: 1.2.2
Summary: pip package for afl
Home-page: UNKNOWN
Author: UNKNOWN
Author-email: UNKNOWN
License: UNKNOWN
Platform: UNKNOWN
